dict_merger/__init__.cpython-310-darwin.so
dict_merger/__init__.py
dict_merger/dynamic_merger.cpython-310-darwin.so
dict_merger/dynamic_merger.py
dict_merger/static_merger.cpython-310-darwin.so
dict_merger-0.0.3.dist-info/LICENSE
dict_merger-0.0.3.dist-info/METADATA
dict_merger-0.0.3.dist-info/WHEEL
dict_merger-0.0.3.dist-info/top_level.txt
dict_merger-0.0.3.dist-info/RECORD
