Metadata-Version: 2.1
Name: dict-merger
Version: 0.0.3
Summary: Cython recursive dictionary merging
Home-page: https://github.com/TeaDove/dict_merger
Author: Peter Ibragimov
License-File: LICENSE
